django_papaye/__init__.py
django_papaye/__main__.py
django_papaye/__pycache__/__init__.cpython-39.pyc
django_papaye/__pycache__/__main__.cpython-39.pyc
django_papaye/src/npm/.parcelrc
django_papaye/src/npm/package.json
django_papaye/src/static/Formation_python.png
django_papaye/src/t_logic/__init__.py
django_papaye/src/t_logic/main.py
django_papaye/src/t_logic/main_mobile.py
django_papaye/src/t_logic/shared/__init__.py
django_papaye/src/t_logic/shared/utils/__init__.py
django_papaye/src/t_logic/shared/utils/pyjs.py
django_papaye/src/t_logic/shared/utils/requires.py
django_papaye/sub_dir/__init__.py
django_papaye/sub_dir/django_papaye.py
django_papaye/sub_dir/__pycache__/__init__.cpython-39.pyc
django_papaye/sub_dir/__pycache__/django_papaye.cpython-39.pyc
django_papaye-0.1.17.dist-info/METADATA
django_papaye-0.1.17.dist-info/WHEEL
django_papaye-0.1.17.dist-info/entry_points.txt
django_papaye-0.1.17.dist-info/top_level.txt
django_papaye-0.1.17.dist-info/RECORD
